mepcocalc/__init__.py
mepcocalc/calc.py
mepcocalc-1.0.dist-info/METADATA
mepcocalc-1.0.dist-info/WHEEL
mepcocalc-1.0.dist-info/top_level.txt
mepcocalc-1.0.dist-info/RECORD
