Metadata-Version: 2.1
Name: mepcocalc
Version: 1.0
Summary: mepco calc is a mini testing calculator
Home-page: UNKNOWN
Author: Thirumoorthy
Author-email: thirumoorthy.gmk@gmail.com
License: Mepco
Platform: UNKNOWN
